odoo8_addon_membership_prorrate_variable_period-8.0.1.0.0.99.dev16-py3.8-nspkg.pth
odoo_addons/membership_prorrate_variable_period/README.rst
odoo_addons/membership_prorrate_variable_period/__init__.py
odoo_addons/membership_prorrate_variable_period/__openerp__.py
odoo_addons/membership_prorrate_variable_period/i18n/ca.po
odoo_addons/membership_prorrate_variable_period/i18n/de.po
odoo_addons/membership_prorrate_variable_period/i18n/es.po
odoo_addons/membership_prorrate_variable_period/i18n/es_MX.po
odoo_addons/membership_prorrate_variable_period/i18n/fi.po
odoo_addons/membership_prorrate_variable_period/i18n/fr.po
odoo_addons/membership_prorrate_variable_period/i18n/fr_CH.po
odoo_addons/membership_prorrate_variable_period/i18n/hr.po
odoo_addons/membership_prorrate_variable_period/i18n/hr_HR.po
odoo_addons/membership_prorrate_variable_period/i18n/it.po
odoo_addons/membership_prorrate_variable_period/i18n/membership_prorrate_variable_period.pot
odoo_addons/membership_prorrate_variable_period/i18n/nl_NL.po
odoo_addons/membership_prorrate_variable_period/i18n/pt_BR.po
odoo_addons/membership_prorrate_variable_period/i18n/pt_PT.po
odoo_addons/membership_prorrate_variable_period/i18n/ro.po
odoo_addons/membership_prorrate_variable_period/i18n/sl.po
odoo_addons/membership_prorrate_variable_period/i18n/tr.po
odoo_addons/membership_prorrate_variable_period/i18n/tr_TR.po
odoo_addons/membership_prorrate_variable_period/i18n/vi_VN.po
odoo_addons/membership_prorrate_variable_period/i18n/zh_CN.po
odoo_addons/membership_prorrate_variable_period/models/__init__.py
odoo_addons/membership_prorrate_variable_period/models/account_invoice.py
odoo_addons/membership_prorrate_variable_period/models/product_template.py
odoo_addons/membership_prorrate_variable_period/static/description/icon.png
odoo_addons/membership_prorrate_variable_period/static/description/icon.svg
odoo_addons/membership_prorrate_variable_period/tests/__init__.py
odoo8_addon_membership_prorrate_variable_period-8.0.1.0.0.99.dev16.dist-info/METADATA
odoo8_addon_membership_prorrate_variable_period-8.0.1.0.0.99.dev16.dist-info/WHEEL
odoo8_addon_membership_prorrate_variable_period-8.0.1.0.0.99.dev16.dist-info/namespace_packages.txt
odoo8_addon_membership_prorrate_variable_period-8.0.1.0.0.99.dev16.dist-info/top_level.txt
odoo8_addon_membership_prorrate_variable_period-8.0.1.0.0.99.dev16.dist-info/RECORD
